ddl2pojo/__init__.py
ddl2pojo/ddl2pojo.tpl
ddl2pojo/main.py
DdlGeneratorTool-1.2.1.dist-info/LICENSE
DdlGeneratorTool-1.2.1.dist-info/METADATA
DdlGeneratorTool-1.2.1.dist-info/WHEEL
DdlGeneratorTool-1.2.1.dist-info/entry_points.txt
DdlGeneratorTool-1.2.1.dist-info/top_level.txt
DdlGeneratorTool-1.2.1.dist-info/RECORD
