Metadata-Version: 2.1
Name: DdlGeneratorTool
Version: 1.2.1
Summary: DDL文件解析程序
Home-page: https://gitee.com/visonforcoding/code-template-tools
Author: visonforcoding
Author-email: visonforcoding@gmail.com
Classifier: Programming Language :: Python :: 3
Classifier: License :: OSI Approved :: MIT License
Classifier: Operating System :: OS Independent
License-File: LICENSE
Requires-Dist: argparse
Requires-Dist: python-string-utils
Requires-Dist: jinja2
